ZhinengShidaiDeKefuZhongxinBiangeYuFazhanFix1/README.md
ZhinengShidaiDeKefuZhongxinBiangeYuFazhanFix1/__init__.py
ZhinengShidaiDeKefuZhongxinBiangeYuFazhanFix1/__main__.py
ZhinengShidaiDeKefuZhongxinBiangeYuFazhanFix1/file.pdf
ZhinengShidaiDeKefuZhongxinBiangeYuFazhanFix1/index.html
zhineng_shidai_de_kefu_zhongxin_biange_yu_fazhan_fix1-2025.3.25.0.dist-info/METADATA
zhineng_shidai_de_kefu_zhongxin_biange_yu_fazhan_fix1-2025.3.25.0.dist-info/WHEEL
zhineng_shidai_de_kefu_zhongxin_biange_yu_fazhan_fix1-2025.3.25.0.dist-info/entry_points.txt
zhineng_shidai_de_kefu_zhongxin_biange_yu_fazhan_fix1-2025.3.25.0.dist-info/top_level.txt
zhineng_shidai_de_kefu_zhongxin_biange_yu_fazhan_fix1-2025.3.25.0.dist-info/RECORD
